csv2txt/__init__.py
csv2txt/cmd.py
csv2txt-0.0.2.dist-info/LICENSE
csv2txt-0.0.2.dist-info/METADATA
csv2txt-0.0.2.dist-info/WHEEL
csv2txt-0.0.2.dist-info/entry_points.txt
csv2txt-0.0.2.dist-info/top_level.txt
csv2txt-0.0.2.dist-info/RECORD
