Metadata-Version: 2.1
Name: csv2txt
Version: 0.0.2
Summary: Convert a csv file to token separator txt file(把csv文件转换为分隔符分隔的文本文件，支持跨行单元格哦)
Home-page: https://github.com/gyk001/csv2txt
Author: gyk001
Author-email: gyk001@gmail.com
License: MIT
Project-URL: Source, https://github.com/gyk001/csv2txt
Project-URL: Documentation, https://github.com/gyk001/csv2txt
Project-URL: Tracker, https://github.com/gyk001/csv2txt/issues
Keywords: csv txt convert
Platform: any
Classifier: Intended Audience :: Developers
Classifier: License :: OSI Approved :: Apache Software License
Classifier: Operating System :: OS Independent
Classifier: Programming Language :: Python
Classifier: Programming Language :: Python :: 2
Classifier: Programming Language :: Python :: 3
Classifier: Topic :: Utilities
Classifier: Topic :: Software Development :: Libraries :: Python Modules
Classifier: Environment :: Console
Classifier: Environment :: MacOS X
Classifier: Environment :: Win32 (MS Windows)
Classifier: Operating System :: MacOS
Classifier: Operating System :: Microsoft :: Windows
Classifier: Operating System :: POSIX :: Linux
